LICENSE
README.md
pyproject.toml
setup.cfg
setup.py
src/slackybot/__init__.py
src/slackybot/exceptions.py
src/slackybot/main.py
src/slackybot/messaging.py
src/slackybot.egg-info/PKG-INFO
src/slackybot.egg-info/SOURCES.txt
src/slackybot.egg-info/dependency_links.txt
src/slackybot.egg-info/requires.txt
src/slackybot.egg-info/top_level.txt
src/slackybot/utilities/__init__.py
src/slackybot/utilities/common.py
src/slackybot/utilities/config.py
src/slackybot/utilities/request_handler.py
tests/test_slack_message_object.py
tests/test_slack_object.py