Metadata-Version: 2.1
Name: slackybot
Version: 1.2.0
Summary: A Python package that helps to interact with the Slack App
Home-page: https://github.com/michalm138/slackybot
Author: michalm138
Author-email: dev.michalm138@gmail.com
Project-URL: Documentation, https://github.com/michalm138/slackybot/blob/main/docs/README.md
Project-URL: Bug Tracker, https://github.com/michalm138/slackybot/issues
Project-URL: Source Code, https://github.com/michalm138/slackybot
Classifier: Programming Language :: Python :: 3
Classifier: License :: OSI Approved :: MIT License
Classifier: Operating System :: OS Independent
Requires-Python: >=3.10
License-File: LICENSE
